MANIFEST.in
setup.py
bs_logic/__init__.py
bs_logic/parser.py
bs_logic.egg-info/PKG-INFO
bs_logic.egg-info/SOURCES.txt
bs_logic.egg-info/dependency_links.txt
bs_logic.egg-info/top_level.txt