Metadata-Version: 2.1
Name: bs-logic
Version: 0.0.11
Summary: Utilities for implementing logical representaions and reasoning systems
Author: Brandon Bennett and Giulia Sindoni
Author-email: B.Bennett@leeds.ac.uk
Classifier: Development Status :: 1 - Planning
